easyml/__init__.py
easyml/models.py
easyml/pipeline.py
easyml/preprocessing.py
onelineml/__init__.py
onelineml/models.py
onelineml/pipeline.py
onelineml/preprocessing.py
onelineml/sourcecode.py
onelineml-0.2.2.dist-info/LICENSE
onelineml-0.2.2.dist-info/METADATA
onelineml-0.2.2.dist-info/WHEEL
onelineml-0.2.2.dist-info/top_level.txt
onelineml-0.2.2.dist-info/RECORD
